legos/__init__.py
legos/constants.py
legos/events.py
legos/forwarding.py
legos/learner.py
legos/metrics.py
legos/torch_utils.py
legos/utils.py
legos/version.py
legos/callbacks/__init__.py
legos/callbacks/callback.py
legos/callbacks/common.py
legos/callbacks/hook.py
legos/callbacks/logger.py
legos/callbacks/lrfinder.py
legos/callbacks/recorder.py
legos/callbacks/schedulers.py
legos/callbacks/skip.py
legos/callbacks/stats.py
legos/callbacks/tqdm_cb.py
legos/datasets/__init__.py
legos/datasets/carvana.py
legos/datasets/common.py
legos/datasets/databunch.py
legos/datasets/filepair.py
legos/datasets/torchvision.py
legos/datasets/transforms.py
legos/io/__init__.py
legos/io/image.py
legos/io/utils.py
legos/layers/__init__.py
legos/layers/common.py
legos/layers/flatten.py
legos/layers/layer_activation.py
legos/layers/upsample.py
legos/models/__init__.py
legos/models/common.py
legos/models/lenet5.py
legos/models/unet.py
legos/models/upsample.py
legos/plugins/__init__.py
legos/plugins/common.py
legos/plugins/inspector.py
legos/plugins/plugins.py
legos/preprocess/__init__.py
legos/preprocess/resize.py
tests/__init__.py
tests/test_torch_utils.py
tests/callbacks/__init__.py
tests/callbacks/test_logger.py
tests/callbacks/test_stats.py
tests/torch/__init__.py
tests/torch/test_tensor.py
legos.ai-0.0.3.1.dist-info/LICENSE
legos.ai-0.0.3.1.dist-info/METADATA
legos.ai-0.0.3.1.dist-info/WHEEL
legos.ai-0.0.3.1.dist-info/top_level.txt
legos.ai-0.0.3.1.dist-info/RECORD
