Metadata-Version: 2.1
Name: legos.ai
Version: 0.0.3.1
Summary: A simple framework for fast protopying of Deep Learning researches.
Home-page: https://github.com/quanhua92/legos
Author: Quan Hua
Author-email: quanhua92@gmail.com
License: Apache
Platform: UNKNOWN
Classifier: License :: OSI Approved :: Apache Software License
Classifier: Programming Language :: Python :: 3
Classifier: Programming Language :: Python :: 3.6
Classifier: Programming Language :: Python :: 3.7
Requires-Dist: numpy
Requires-Dist: matplotlib
Requires-Dist: tqdm
Requires-Dist: albumentations
Requires-Dist: beautifultable
Requires-Dist: torchprof
Requires-Dist: hiddenlayer
